serverip/__init__.py
serverip/myserverip.py
myserverip-1.0.0.dist-info/METADATA
myserverip-1.0.0.dist-info/WHEEL
myserverip-1.0.0.dist-info/entry_points.txt
myserverip-1.0.0.dist-info/top_level.txt
myserverip-1.0.0.dist-info/RECORD
