Metadata-Version: 2.4
Name: myserverip
Version: 1.0.0
Summary: A Python library to get server's public IP address from system interfaces
Home-page: https://github.com/daoudiyounes/serverip
Author: younes daoudi
Author-email: your.email@example.com
Project-URL: Bug Reports, https://github.com/daoudiyounes/serverip/issues
Project-URL: Source, https://github.com/daoudiyounes/serverip
Keywords: server ip address network interface system local
Classifier: Development Status :: 4 - Beta
Classifier: Intended Audience :: Developers
Classifier: Topic :: Internet :: WWW/HTTP
Classifier: Topic :: System :: Networking
Classifier: License :: OSI Approved :: MIT License
Classifier: Programming Language :: Python :: 3
Requires-Python: >=3
Requires-Dist: netifaces>=0.11.0
Provides-Extra: dev
Requires-Dist: pytest>=6.0; extra == "dev"
Requires-Dist: pytest-cov>=2.0; extra == "dev"
Requires-Dist: black>=21.0; extra == "dev"
Requires-Dist: flake8>=3.8; extra == "dev"
Dynamic: author
Dynamic: author-email
Dynamic: classifier
Dynamic: description
Dynamic: description-content-type
Dynamic: home-page
Dynamic: keywords
Dynamic: project-url
Dynamic: provides-extra
Dynamic: requires-dist
Dynamic: requires-python
Dynamic: summary
